{
  "project_info": {
    "project_number": "735291525415",
    "project_id": "chronos-point",
    "storage_bucket": "chronos-point.appspot.com"
  },
  "client": [
    {
      "client_info": {
        "mobilesdk_app_id": "1:735291525415:android:f59a1138fef172a2358102",
        "android_client_info": {
          "package_name": "chronospoint.app"
        }
      },
      "oauth_client": [],
      "api_key": [
        {
          "current_key": "AIzaSyA2GA5IB8MvAr9qzy8EZ-srsxOobvWzXac"
        }
      ],
      "services": {
        "appinvite_service": {
          "other_platform_oauth_client": []
        }
      }
    }
  ],
  "configuration_version": "1"
}